dse/__init__.py
dse/auth.py
dse/buffer.pxd
dse/bytesio.cp37-win_amd64.pyd
dse/bytesio.pxd
dse/bytesio.pyx
dse/cluster.cp37-win_amd64.pyd
dse/cluster.py
dse/cmurmur3.c
dse/cmurmur3.cp37-win_amd64.pyd
dse/compat.py
dse/concurrent.cp37-win_amd64.pyd
dse/concurrent.py
dse/connection.cp37-win_amd64.pyd
dse/connection.py
dse/cqltypes.cp37-win_amd64.pyd
dse/cqltypes.py
dse/cython_deps.py
dse/cython_marshal.cp37-win_amd64.pyd
dse/cython_marshal.pyx
dse/cython_utils.cp37-win_amd64.pyd
dse/cython_utils.pxd
dse/cython_utils.pyx
dse/deserializers.cp37-win_amd64.pyd
dse/deserializers.pxd
dse/deserializers.pyx
dse/encoder.py
dse/hosts.cp37-win_amd64.pyd
dse/hosts.py
dse/ioutils.cp37-win_amd64.pyd
dse/ioutils.pyx
dse/marshal.py
dse/metadata.cp37-win_amd64.pyd
dse/metadata.py
dse/metrics.py
dse/murmur3.py
dse/numpyFlags.h
dse/numpy_parser.cp37-win_amd64.pyd
dse/numpy_parser.pyx
dse/obj_parser.cp37-win_amd64.pyd
dse/obj_parser.pyx
dse/parsing.cp37-win_amd64.pyd
dse/parsing.pxd
dse/parsing.pyx
dse/policies.py
dse/protocol.cp37-win_amd64.pyd
dse/protocol.py
dse/query.cp37-win_amd64.pyd
dse/query.py
dse/row_parser.cp37-win_amd64.pyd
dse/row_parser.pyx
dse/timestamps.py
dse/tuple.pxd
dse/type_codes.pxd
dse/type_codes.py
dse/util.cp37-win_amd64.pyd
dse/util.py
dse/cqlengine/__init__.py
dse/cqlengine/columns.py
dse/cqlengine/connection.py
dse/cqlengine/functions.py
dse/cqlengine/management.py
dse/cqlengine/models.py
dse/cqlengine/named.py
dse/cqlengine/operators.py
dse/cqlengine/query.py
dse/cqlengine/statements.py
dse/cqlengine/usertype.py
dse/datastax/__init__.py
dse/datastax/cloud/__init__.py
dse/graph/__init__.py
dse/graph/graphson.py
dse/graph/query.py
dse/graph/types.py
dse/insights/__init__.py
dse/insights/registry.py
dse/insights/reporter.py
dse/insights/serializers.py
dse/insights/util.py
dse/io/__init__.py
dse/io/asyncioreactor.py
dse/io/asyncorereactor.py
dse/io/eventletreactor.py
dse/io/geventreactor.py
dse/io/libevreactor.py
dse/io/libevwrapper.c
dse/io/twistedreactor.py
dse_driver-2.11.1.dist-info/LICENSE
dse_driver-2.11.1.dist-info/METADATA
dse_driver-2.11.1.dist-info/WHEEL
dse_driver-2.11.1.dist-info/top_level.txt
dse_driver-2.11.1.dist-info/RECORD
