Metadata-Version: 2.1
Name: dse-driver
Version: 2.11.1
Summary: DataStax Enterprise Python Driver
Home-page: http://docs.datastax.com/en/developer/python-dse-driver/
Author: Tyler Hobbs
Author-email: tyler@datastax.com
License: DataStax DSE Driver License http://www.datastax.com/terms/datastax-dse-driver-license-terms
Keywords: cassandra,cql,orm,dse,graph
Platform: UNKNOWN
Classifier: Development Status :: 5 - Production/Stable
Classifier: Intended Audience :: Developers
Classifier: License :: Other/Proprietary License
Classifier: Natural Language :: English
Classifier: Operating System :: OS Independent
Classifier: Programming Language :: Python
Classifier: Programming Language :: Python :: 2.7
Classifier: Programming Language :: Python :: 3.4
Classifier: Programming Language :: Python :: 3.5
Classifier: Programming Language :: Python :: 3.6
Classifier: Programming Language :: Python :: 3.7
Classifier: Programming Language :: Python :: Implementation :: CPython
Classifier: Programming Language :: Python :: Implementation :: PyPy
Classifier: Topic :: Software Development :: Libraries :: Python Modules
Requires-Dist: six (>=1.9)
Requires-Dist: geomet (<0.2,>=0.1)
